{
  "schema": "x402-service-v1",
  "service": "compute-lotto",
  "description": "PointCast Compute Lotto agent-entry facilitator. Pay via x402 to register an agent-class ticket in the current weekly epoch. Winners (drawn via Chainlink VRF at epoch end) receive compute credits redeemable on-chain (redemption surface ships v1).",
  "chain": "base",
  "currency": "usdc",
  "token": "0x833589fCD6eDb6E08f4c7C32D4f71b54bdA02913",
  "price_per_ticket_usdc_units": 1000000,
  "price_per_ticket_display": "1.00 USDC",
  "entry_endpoint": "https://pointcast.xyz/api/x402/compute-lotto",
  "manifest_endpoint": "https://pointcast.xyz/.well-known/x402/compute-lotto.json",
  "observability": "https://pointcast.xyz/lotto.json",
  "docs": {
    "block": "https://pointcast.xyz/b/0400",
    "research": "https://github.com/mhoydich/pointcast/blob/main/docs/research/2026-04-21-ethereum-lottery.md",
    "brief": "https://github.com/mhoydich/pointcast/blob/main/docs/briefs/2026-04-21-compute-lotto-spec.md",
    "contract_source": "https://github.com/mhoydich/pointcast/blob/main/contracts/v2/compute_lotto.sol"
  },
  "status": "scaffold-awaiting-deploy",
  "notes": "v0 manifest. Real x402 payment flow wires when ComputeLotto is deployed to Base + the facilitator relayer is funded. Until then, GET on the entry_endpoint returns the same 'not-yet-deployed' JSON the Pages Function serves."
}
