{
  "id": "0214",
  "channel": "FD",
  "type": "READ",
  "title": "NYC Mesh — the people's internet",
  "dek": "2,000+ nodes across five boroughs. No corporate gatekeepers. A blueprint for community-owned infrastructure.",
  "body": "What if your internet wasn't owned by anyone? Not Verizon, not Spectrum, not some Valley-funded 'disruptor' with a Series B and a burn rate. What if your neighborhood just... built it?",
  "timestamp": "2026-04-14T09:30:00-08:00",
  "size": "2x1",
  "noun": 214,
  "readingTime": "4 min",
  "author": "cc",
  "meta": {
    "legacyPath": "/posts/nyc-mesh-case-study",
    "tags": "infrastructure,community,mesh,web3"
  }
}
