{
  "id": "0244",
  "channel": "ESC",
  "type": "READ",
  "title": "Become a beacon — the 25-mile radius",
  "dek": "PointCast anchors in El Segundo. Draw a 25-mile circle and you've got most of the South Bay, the Westside, part of DTLA, and a slice of Long Beach. That's the service area.",
  "body": "El Segundo is one square mile. It has a Main Street. It has a beach. It has an Air Force base on the south edge and a tech corridor on the east. It is a specific kind of small town — big enough to matter, small enough to know.\n\nThe 25-mile radius from Main + Grand, drawn on any map, covers about 2.4 million people. That's the South Bay, the Westside, the Harbor Area, industrial Hawthorne through Compton, downtown LA's western edge, part of Long Beach. It's reachable by car in under 40 minutes. It's reachable on a bike if you're ambitious. Most of it is reachable via the K line if you start walking from the Metro.\n\nWhat if PointCast becomes a beacon for that radius?\n\n**Mesh first.** Start a neighborhood mesh in El Segundo (Block 0240). First hop: Manhattan + Hermosa, because they're three miles south and they share beach infrastructure. Second hop: Redondo + Westchester, because they're on opposite bearings and the supernodes cover a lot of ground. Year two: Venice + Culver City + Santa Monica, the creative spine of the Westside. Year three: Inglewood + Compton, communities that have been underserved by broadband incumbents for decades. Each mesh chapter inherits the playbook — hardware pool, governance rubric, backhaul agreements.\n\n**Third spaces second.** The Block 0242 archetype (pickleball + nature + food + saunas + pool + art) replicates. First instance is El Segundo; year two targets are Venice, Torrance, Inglewood, Long Beach. Members of any are members of all. The network competes with Equinox on the luxury axis (and loses) but wins on the *third-place* axis — the feeling that you'd come to the building even without the amenities.\n\n**DAO real estate third.** ESREF (Block 0241) buys commercial property in 90245 year one. A year-two DAO vote could expand the mandate to the full 25-mile radius, on a per-property basis. We'd own a Main Street building in El Segundo. We'd own a corner property in Redondo. We'd own a warehouse in Hawthorne that's cheaper per square foot than the AMC in Inglewood.\n\n**Cross-programming fourth.** A pickleball league where teams are made of members from two different cities. A mesh-workshop where Inglewood installs bring gear and Palos Verdes installs bring rooftop access. A third-space quarterly convention where all fifty facilities send a delegate. A dispatch archive where a Mar Vista dispatch cites a Long Beach dispatch.\n\nThe beacon metaphor is literal. A beacon is a fixed light that other things navigate by. El Segundo is the fixed point; the 25-mile circle is the horizon; the neighborhoods inside it are the ships. PointCast's work is to be bright enough to be seen — and the way sites become bright is by doing real things in the open. /dao is the governance beacon. /publish is the thinking beacon. /b/0242 is the civic beacon. The more primitives we ship, the further the light reaches.\n\nIn ten years, there's either a network of community-owned third places blanketing the South Bay, or there isn't. The difference is a neighborhood-level choice to start — in El Segundo, this year.",
  "timestamp": "2026-04-18T13:30:00-08:00",
  "size": "3x2",
  "noun": 91,
  "readingTime": "5 min",
  "meta": {
    "topic": "community-growth",
    "location": "El Segundo + 25mi radius",
    "tag": "beacon",
    "references": "0240,0241,0242"
  }
}
