{
  "id": "0275",
  "channel": "SPN",
  "type": "LISTEN",
  "title": "Wild Mountain Honey · a Mike playlist · current state from El Segundo",
  "dek": "Mike's own Spotify playlist, shared in chat. Current-state snapshot attached.",
  "body": "boddingtions and wild mountain honey\n\n710 labs z, current state, el segundo california",
  "timestamp": "2026-04-18T21:20:00-08:00",
  "size": "2x1",
  "noun": 222,
  "media": {
    "kind": "embed",
    "src": "https://open.spotify.com/embed/playlist/3zBaNJxJuBxpCrvmWq5wta",
    "thumbnail": "https://noun.pics/222.svg"
  },
  "external": {
    "url": "https://open.spotify.com/playlist/3zBaNJxJuBxpCrvmWq5wta?si=2f996671ba7147dc",
    "label": "Open in Spotify"
  },
  "author": "mike",
  "source": "Mike chat 2026-04-18 ~9:20pm PT: shared the Spotify playlist \"Wild Mountain Honey\" (creator: mhoydich) alongside a one-line current-state note mentioning boddingtons + 710 labs z + El Segundo. Body preserves his exact text.",
  "companions": [
    { "id": "0263", "label": "November Rain · YeePlayer", "surface": "yee" },
    { "id": "0264", "label": "Purple Rain · YeePlayer",   "surface": "yee" },
    { "id": "0262", "label": "Alan Watts · guided meditation · YeePlayer", "surface": "yee" },
    { "id": "0236", "label": "Chakra tune-up · YeePlayer", "surface": "yee" },
    { "id": "0277", "label": "De La Soul is Dead · the other Mike playlist", "surface": "block" }
  ],
  "mood": "rainy-week",
  "meta": {
    "tag": "playlist",
    "medium": "spotify",
    "creator": "mhoydich",
    "location": "El Segundo, California"
  }
}
